trigger/__init__.py
trigger/cmds.py
trigger/exceptions.py
trigger/gorc.py
trigger/netscreen.py
trigger/rancid.py
trigger/tacacsrc.py
trigger/twister.py
trigger/acl/__init__.py
trigger/acl/autoacl.py
trigger/acl/db.py
trigger/acl/dicts.py
trigger/acl/grammar.py
trigger/acl/ios.py
trigger/acl/junos.py
trigger/acl/models.py
trigger/acl/parser.py
trigger/acl/queue.py
trigger/acl/support.py
trigger/acl/tools.py
trigger/changemgmt/__init__.py
trigger/changemgmt/bounce.py
trigger/conf/__init__.py
trigger/conf/global_settings.py
trigger/contrib/__init__.py
trigger/contrib/commando/__init__.py
trigger/contrib/commando/plugins/__init__.py
trigger/contrib/commando/plugins/config_device.py
trigger/contrib/commando/plugins/gather_info.py
trigger/contrib/commando/plugins/show_clock.py
trigger/contrib/commando/plugins/show_version.py
trigger/contrib/docommand/__init__.py
trigger/contrib/docommand/core.py
trigger/contrib/xmlrpc/__init__.py
trigger/contrib/xmlrpc/server.py
trigger/netdevices/__init__.py
trigger/netdevices/loader.py
trigger/netdevices/loaders/__init__.py
trigger/netdevices/loaders/filesystem.py
trigger/netdevices/loaders/mongodb.py
trigger/packages/__init__.py
trigger/packages/peewee.py
trigger/packages/tftpy/__init__.py
trigger/packages/tftpy/TftpClient.py
trigger/packages/tftpy/TftpContexts.py
trigger/packages/tftpy/TftpPacketFactory.py
trigger/packages/tftpy/TftpPacketTypes.py
trigger/packages/tftpy/TftpServer.py
trigger/packages/tftpy/TftpShared.py
trigger/packages/tftpy/TftpStates.py
trigger/utils/__init__.py
trigger/utils/cli.py
trigger/utils/importlib.py
trigger/utils/network.py
trigger/utils/rcs.py
trigger/utils/url.py
trigger/utils/xmltodict.py
trigger/utils/notifications/__init__.py
trigger/utils/notifications/core.py
trigger/utils/notifications/events.py
trigger/utils/notifications/handlers.py
trigger-1.5.2.data/scripts/acl
trigger-1.5.2.data/scripts/acl_script
trigger-1.5.2.dist-info/DESCRIPTION.rst
trigger-1.5.2.dist-info/METADATA
trigger-1.5.2.dist-info/metadata.json
trigger-1.5.2.dist-info/RECORD
trigger-1.5.2.dist-info/top_level.txt
trigger-1.5.2.dist-info/WHEEL
