Metadata-Version: 2.0
Name: trigger
Version: 1.5.2
Summary: Trigger is a framework and suite of tools for configuring network devices
Home-page: https://github.com/trigger/trigger
Author: Jathan McCollum
Author-email: jathanism@aol.com
License: BSD
Keywords: Configuration Management,IANA,IEEE,IP,IP Address,IPv4,IPv6,Firewall,Network Automation,Networking,Network Engineering,Network Configuration,Network Security,Router,Systems Administration,Security,Switch
Platform: UNKNOWN
Classifier: Development Status :: 6 - Mature
Classifier: Environment :: Console
Classifier: Environment :: Console :: Curses
Classifier: Framework :: Twisted
Classifier: Intended Audience :: Developers
Classifier: Intended Audience :: Education
Classifier: Intended Audience :: Information Technology
Classifier: Intended Audience :: Other Audience
Classifier: Intended Audience :: Science/Research
Classifier: Intended Audience :: System Administrators
Classifier: Intended Audience :: Telecommunications Industry
Classifier: Natural Language :: English
Classifier: License :: OSI Approved :: BSD License
Classifier: Operating System :: OS Independent
Classifier: Programming Language :: Python
Classifier: Programming Language :: Python :: 2.6
Classifier: Programming Language :: Python :: 2.7
Classifier: Topic :: Internet
Classifier: Topic :: Scientific/Engineering :: Interface Engine/Protocol Translator
Classifier: Topic :: Security
Classifier: Topic :: Software Development
Classifier: Topic :: Software Development :: Libraries :: Python Modules
Classifier: Topic :: System :: Networking
Classifier: Topic :: System :: Networking :: Firewalls
Classifier: Topic :: System :: Networking :: Monitoring
Classifier: Topic :: System :: Operating System
Classifier: Topic :: System :: Systems Administration
Classifier: Topic :: Terminals :: Telnet
Classifier: Topic :: Utilities
Requires-Dist: IPy (>=0.73)
Requires-Dist: Twisted
Requires-Dist: pyasn1
Requires-Dist: pycrypto
Requires-Dist: pyparsing (==1.5.7)
Requires-Dist: pytz (<=2014.2)
Requires-Dist: SimpleParse
Requires-Dist: redis
